{
  "function_reference_rate": {
    "numerator": 109,
    "denominator": 111,
    "rate": 0.9819819819819819
  },
  "anchor_consistency_rate": {
    "numerator": 690,
    "denominator": 690,
    "rate": 1.0
  },
  "equation_unit_coverage": {
    "numerator": 34,
    "denominator": 36,
    "rate": 0.9444444444444444
  },
  "sinks_callgraph_documented": true,
  "holes": [
    "marsdisk/physics/collide.py#prepare_collision_kernel_workspace",
    "marsdisk/physics/radiation.py#qpr_lookup_array"
  ]
}
